pydtnsim/__init__.py
pydtnsim/contact.py
pydtnsim/contact_graph.py
pydtnsim/contact_plan.py
pydtnsim/packet.py
pydtnsim/simulator.py
pydtnsim/backend/__init__.py
pydtnsim/backend/qsim.py
pydtnsim/monitors/__init__.py
pydtnsim/monitors/base_monitor.py
pydtnsim/monitors/monitor_notifier.py
pydtnsim/nodes/__init__.py
pydtnsim/nodes/simple_cgr_node.py
pydtnsim/packet_generators/__init__.py
pydtnsim/packet_generators/base_packet_generator.py
pydtnsim/packet_generators/batch_packet_generator.py
pydtnsim/packet_generators/continuous_packet_generator.py
pydtnsim/routing/__init__.py
pydtnsim/routing/cgr_anchor.py
pydtnsim/routing/cgr_basic.py
pydtnsim/routing/cgr_utils.py
pydtnsim/routing/dijkstra.py
pydtnsim/routing/scgr.py
tests/__init__.py
tests/run_examples.py
tests/unittests/__init__.py
tests/unittests/test_cgr.py
tests/unittests/test_contact.py
tests/unittests/test_contact_graph.py
tests/unittests/test_contact_plan.py
tests/unittests/test_dijkstra.py
tests/unittests/test_integration.py
tests/unittests/test_monitor_notifier.py
tests/unittests/test_simple_cgr_node.py
pydtnsim-0.1.1.dist-info/LICENSE
pydtnsim-0.1.1.dist-info/METADATA
pydtnsim-0.1.1.dist-info/WHEEL
pydtnsim-0.1.1.dist-info/top_level.txt
pydtnsim-0.1.1.dist-info/RECORD
