Metadata-Version: 2.1
Name: pydtnsim
Version: 0.1.1
Summary: A discrete event simulation library for DTN
Home-page: https://github.com/ducktec/pydtnsim
Author: Robert Wiewel
Author-email: dev@ducktec.de
License: MIT
Project-URL: Source Code, https://github.com/ducktec/pydtnsim
Project-URL: Bug Tracker, https://github.com/ducktec/pydtnsim/issues
Keywords: delay-tolerant-networking,routing,simulation,dtn,cgr
Platform: UNKNOWN
Classifier: Development Status :: 3 - Alpha
Classifier: Environment :: Console
Classifier: Intended Audience :: Developers
Classifier: Intended Audience :: Information Technology
Classifier: Intended Audience :: Education
Classifier: Intended Audience :: Science/Research
Classifier: Natural Language :: English
Classifier: License :: OSI Approved :: MIT License
Classifier: Programming Language :: Python
Classifier: Programming Language :: Python :: 3
Classifier: Programming Language :: Python :: 3.7
Classifier: Topic :: Software Development
Requires-Python: >=3.7.0
License-File: LICENSE
Requires-Dist: networkx (<3.0,>=2.0)
Requires-Dist: tqdm (<5.0,>=4.0)
Requires-Dist: jsonschema (<3.0,>=2.0)
Provides-Extra: dev
Requires-Dist: pytest (<4.0,>=3.0) ; extra == 'dev'
Requires-Dist: Sphinx (<2.0,>=1.0) ; extra == 'dev'
Requires-Dist: sphinx-rtd-theme (==0.4.2) ; extra == 'dev'
Requires-Dist: pylint (<3.0,>=2.0) ; extra == 'dev'
Requires-Dist: pydocstyle (<3.0,>2.0) ; extra == 'dev'
Requires-Dist: termcolor (<2.0,>=1.0) ; extra == 'dev'
